{
  "stock_id": "6609",
  "stock_name": "瀧澤科",
  "updated_at": "2026-07-15T19:22:09",
  "price": [
    {
      "date": "2026-05-04",
      "open": 39.5,
      "high": 41.7,
      "low": 39.4,
      "close": 40.85,
      "volume": 960624.0,
      "ma5": null,
      "ma10": null,
      "ma20": null,
      "ma60": null,
      "ma120": null,
      "ma240": null
    },
    {
      "date": "2026-05-05",
      "open": 40.85,
      "high": 42.8,
      "low": 40.5,
      "close": 41.55,
      "volume": 1012672.0,
      "ma5": null,
      "ma10": null,
      "ma20": null,
      "ma60": null,
      "ma120": null,
      "ma240": null
    },
    {
      "date": "2026-05-06",
      "open": 41.25,
      "high": 44.5,
      "low": 40.45,
      "close": 44.0,
      "volume": 2280384.0,
      "ma5": null,
      "ma10": null,
      "ma20": null,
      "ma60": null,
      "ma120": null,
      "ma240": null
    },
    {
      "date": "2026-05-07",
      "open": 44.0,
      "high": 45.8,
      "low": 43.05,
      "close": 43.6,
      "volume": 1638122.0,
      "ma5": null,
      "ma10": null,
      "ma20": null,
      "ma60": null,
      "ma120": null,
      "ma240": null
    },
    {
      "date": "2026-05-08",
      "open": 43.6,
      "high": 45.45,
      "low": 42.5,
      "close": 42.6,
      "volume": 1144343.0,
      "ma5": 42.52,
      "ma10": null,
      "ma20": null,
      "ma60": null,
      "ma120": null,
      "ma240": null
    },
    {
      "date": "2026-05-11",
      "open": 43.7,
      "high": 44.7,
      "low": 42.5,
      "close": 43.3,
      "volume": 734859.0,
      "ma5": 43.01,
      "ma10": null,
      "ma20": null,
      "ma60": null,
      "ma120": null,
      "ma240": null
    },
    {
      "date": "2026-05-12",
      "open": 43.65,
      "high": 43.95,
      "low": 40.75,
      "close": 41.65,
      "volume": 721047.0,
      "ma5": 43.03,
      "ma10": null,
      "ma20": null,
      "ma60": null,
      "ma120": null,
      "ma240": null
    },
    {
      "date": "2026-05-13",
      "open": 41.6,
      "high": 41.6,
      "low": 40.1,
      "close": 40.5,
      "volume": 461320.0,
      "ma5": 42.33,
      "ma10": null,
      "ma20": null,
      "ma60": null,
      "ma120": null,
      "ma240": null
    },
    {
      "date": "2026-05-14",
      "open": 40.6,
      "high": 41.25,
      "low": 40.2,
      "close": 40.5,
      "volume": 241863.0,
      "ma5": 41.71,
      "ma10": null,
      "ma20": null,
      "ma60": null,
      "ma120": null,
      "ma240": null
    },
    {
      "date": "2026-05-15",
      "open": 40.8,
      "high": 42.6,
      "low": 40.8,
      "close": 41.1,
      "volume": 514198.0,
      "ma5": 41.41,
      "ma10": 41.96,
      "ma20": null,
      "ma60": null,
      "ma120": null,
      "ma240": null
    },
    {
      "date": "2026-05-18",
      "open": 41.1,
      "high": 43.0,
      "low": 39.7,
      "close": 42.55,
      "volume": 627299.0,
      "ma5": 41.26,
      "ma10": 42.13,
      "ma20": null,
      "ma60": null,
      "ma120": null,
      "ma240": null
    },
    {
      "date": "2026-05-19",
      "open": 43.1,
      "high": 43.25,
      "low": 41.35,
      "close": 42.2,
      "volume": 584127.0,
      "ma5": 41.37,
      "ma10": 42.2,
      "ma20": null,
      "ma60": null,
      "ma120": null,
      "ma240": null
    },
    {
      "date": "2026-05-20",
      "open": 41.8,
      "high": 42.2,
      "low": 40.8,
      "close": 41.25,
      "volume": 280861.0,
      "ma5": 41.52,
      "ma10": 41.92,
      "ma20": null,
      "ma60": null,
      "ma120": null,
      "ma240": null
    },
    {
      "date": "2026-05-21",
      "open": 42.0,
      "high": 42.4,
      "low": 41.8,
      "close": 42.15,
      "volume": 314826.0,
      "ma5": 41.85,
      "ma10": 41.78,
      "ma20": null,
      "ma60": null,
      "ma120": null,
      "ma240": null
    },
    {
      "date": "2026-05-22",
      "open": 42.85,
      "high": 46.35,
      "low": 42.5,
      "close": 46.35,
      "volume": 3579530.0,
      "ma5": 42.9,
      "ma10": 42.15,
      "ma20": null,
      "ma60": null,
      "ma120": null,
      "ma240": null
    },
    {
      "date": "2026-05-25",
      "open": 46.75,
      "high": 49.45,
      "low": 46.6,
      "close": 49.4,
      "volume": 4658895.0,
      "ma5": 44.27,
      "ma10": 42.77,
      "ma20": null,
      "ma60": null,
      "ma120": null,
      "ma240": null
    },
    {
      "date": "2026-05-26",
      "open": 50.0,
      "high": 50.0,
      "low": 46.25,
      "close": 47.85,
      "volume": 1958437.0,
      "ma5": 45.4,
      "ma10": 43.38,
      "ma20": null,
      "ma60": null,
      "ma120": null,
      "ma240": null
    },
    {
      "date": "2026-05-27",
      "open": 47.8,
      "high": 47.8,
      "low": 44.85,
      "close": 46.4,
      "volume": 1315528.0,
      "ma5": 46.43,
      "ma10": 43.98,
      "ma20": null,
      "ma60": null,
      "ma120": null,
      "ma240": null
    },
    {
      "date": "2026-05-28",
      "open": 46.85,
      "high": 47.65,
      "low": 44.15,
      "close": 44.85,
      "volume": 966910.0,
      "ma5": 46.97,
      "ma10": 44.41,
      "ma20": null,
      "ma60": null,
      "ma120": null,
      "ma240": null
    },
    {
      "date": "2026-05-29",
      "open": 45.15,
      "high": 48.9,
      "low": 44.5,
      "close": 45.95,
      "volume": 1734131.0,
      "ma5": 46.89,
      "ma10": 44.9,
      "ma20": 43.43,
      "ma60": null,
      "ma120": null,
      "ma240": null
    },
    {
      "date": "2026-06-01",
      "open": 46.35,
      "high": 49.8,
      "low": 45.35,
      "close": 47.85,
      "volume": 1817624.0,
      "ma5": 46.58,
      "ma10": 45.42,
      "ma20": 43.78,
      "ma60": null,
      "ma120": null,
      "ma240": null
    },
    {
      "date": "2026-06-02",
      "open": 48.05,
      "high": 48.05,
      "low": 45.8,
      "close": 47.2,
      "volume": 1064052.0,
      "ma5": 46.45,
      "ma10": 45.92,
      "ma20": 44.06,
      "ma60": null,
      "ma120": null,
      "ma240": null
    },
    {
      "date": "2026-06-03",
      "open": 47.25,
      "high": 48.95,
      "low": 46.55,
      "close": 46.8,
      "volume": 899210.0,
      "ma5": 46.53,
      "ma10": 46.48,
      "ma20": 44.2,
      "ma60": null,
      "ma120": null,
      "ma240": null
    },
    {
      "date": "2026-06-04",
      "open": 46.8,
      "high": 47.05,
      "low": 45.25,
      "close": 45.6,
      "volume": 751974.0,
      "ma5": 46.68,
      "ma10": 46.83,
      "ma20": 44.3,
      "ma60": null,
      "ma120": null,
      "ma240": null
    },
    {
      "date": "2026-06-05",
      "open": 45.85,
      "high": 47.2,
      "low": 44.6,
      "close": 45.9,
      "volume": 668175.0,
      "ma5": 46.67,
      "ma10": 46.78,
      "ma20": 44.47,
      "ma60": null,
      "ma120": null,
      "ma240": null
    },
    {
      "date": "2026-06-08",
      "open": 41.4,
      "high": 44.55,
      "low": 41.4,
      "close": 44.1,
      "volume": 811155.0,
      "ma5": 45.92,
      "ma10": 46.25,
      "ma20": 44.51,
      "ma60": null,
      "ma120": null,
      "ma240": null
    },
    {
      "date": "2026-06-09",
      "open": 44.15,
      "high": 44.85,
      "low": 43.4,
      "close": 44.3,
      "volume": 572928.0,
      "ma5": 45.34,
      "ma10": 45.9,
      "ma20": 44.64,
      "ma60": null,
      "ma120": null,
      "ma240": null
    },
    {
      "date": "2026-06-10",
      "open": 43.5,
      "high": 45.0,
      "low": 42.35,
      "close": 43.0,
      "volume": 809863.0,
      "ma5": 44.58,
      "ma10": 45.55,
      "ma20": 44.77,
      "ma60": null,
      "ma120": null,
      "ma240": null
    },
    {
      "date": "2026-06-11",
      "open": 41.9,
      "high": 42.95,
      "low": 40.35,
      "close": 41.7,
      "volume": 705047.0,
      "ma5": 43.8,
      "ma10": 45.24,
      "ma20": 44.83,
      "ma60": null,
      "ma120": null,
      "ma240": null
    },
    {
      "date": "2026-06-12",
      "open": 41.75,
      "high": 42.75,
      "low": 41.6,
      "close": 41.9,
      "volume": 320388.0,
      "ma5": 43.0,
      "ma10": 44.83,
      "ma20": 44.87,
      "ma60": null,
      "ma120": null,
      "ma240": null
    },
    {
      "date": "2026-06-15",
      "open": 42.35,
      "high": 42.65,
      "low": 41.2,
      "close": 41.2,
      "volume": 378766.0,
      "ma5": 42.42,
      "ma10": 44.17,
      "ma20": 44.8,
      "ma60": null,
      "ma120": null,
      "ma240": null
    },
    {
      "date": "2026-06-16",
      "open": 41.2,
      "high": 41.25,
      "low": 40.6,
      "close": 41.0,
      "volume": 207073.0,
      "ma5": 41.76,
      "ma10": 43.55,
      "ma20": 44.74,
      "ma60": null,
      "ma120": null,
      "ma240": null
    },
    {
      "date": "2026-06-17",
      "open": 40.6,
      "high": 41.85,
      "low": 40.3,
      "close": 41.2,
      "volume": 279006.0,
      "ma5": 41.4,
      "ma10": 42.99,
      "ma20": 44.73,
      "ma60": null,
      "ma120": null,
      "ma240": null
    },
    {
      "date": "2026-06-18",
      "open": 40.9,
      "high": 41.45,
      "low": 40.8,
      "close": 41.35,
      "volume": 385044.0,
      "ma5": 41.33,
      "ma10": 42.56,
      "ma20": 44.7,
      "ma60": null,
      "ma120": null,
      "ma240": null
    },
    {
      "date": "2026-06-22",
      "open": 41.3,
      "high": 43.6,
      "low": 41.3,
      "close": 42.3,
      "volume": 499821.0,
      "ma5": 41.41,
      "ma10": 42.2,
      "ma20": 44.49,
      "ma60": null,
      "ma120": null,
      "ma240": null
    },
    {
      "date": "2026-06-23",
      "open": 42.6,
      "high": 42.6,
      "low": 40.7,
      "close": 41.45,
      "volume": 424427.0,
      "ma5": 41.46,
      "ma10": 41.94,
      "ma20": 44.1,
      "ma60": null,
      "ma120": null,
      "ma240": null
    },
    {
      "date": "2026-06-24",
      "open": 41.35,
      "high": 41.65,
      "low": 40.35,
      "close": 40.7,
      "volume": 322254.0,
      "ma5": 41.4,
      "ma10": 41.58,
      "ma20": 43.74,
      "ma60": null,
      "ma120": null,
      "ma240": null
    },
    {
      "date": "2026-06-25",
      "open": 40.7,
      "high": 41.0,
      "low": 40.25,
      "close": 40.65,
      "volume": 206044.0,
      "ma5": 41.29,
      "ma10": 41.34,
      "ma20": 43.45,
      "ma60": null,
      "ma120": null,
      "ma240": null
    },
    {
      "date": "2026-06-26",
      "open": 40.15,
      "high": 40.7,
      "low": 39.2,
      "close": 39.3,
      "volume": 326375.0,
      "ma5": 40.88,
      "ma10": 41.11,
      "ma20": 43.17,
      "ma60": null,
      "ma120": null,
      "ma240": null
    },
    {
      "date": "2026-06-29",
      "open": 39.75,
      "high": 40.75,
      "low": 38.65,
      "close": 39.15,
      "volume": 214939.0,
      "ma5": 40.25,
      "ma10": 40.83,
      "ma20": 42.83,
      "ma60": null,
      "ma120": null,
      "ma240": null
    },
    {
      "date": "2026-06-30",
      "open": 39.2,
      "high": 40.0,
      "low": 39.2,
      "close": 39.8,
      "volume": 152591.0,
      "ma5": 39.92,
      "ma10": 40.69,
      "ma20": 42.43,
      "ma60": null,
      "ma120": null,
      "ma240": null
    },
    {
      "date": "2026-07-01",
      "open": 39.85,
      "high": 41.45,
      "low": 39.85,
      "close": 40.0,
      "volume": 424741.0,
      "ma5": 39.78,
      "ma10": 40.59,
      "ma20": 42.07,
      "ma60": null,
      "ma120": null,
      "ma240": null
    },
    {
      "date": "2026-07-02",
      "open": 39.65,
      "high": 43.0,
      "low": 39.65,
      "close": 41.9,
      "volume": 516797.0,
      "ma5": 40.03,
      "ma10": 40.66,
      "ma20": 41.83,
      "ma60": null,
      "ma120": null,
      "ma240": null
    },
    {
      "date": "2026-07-03",
      "open": 42.05,
      "high": 42.55,
      "low": 41.9,
      "close": 41.95,
      "volume": 263132.0,
      "ma5": 40.56,
      "ma10": 40.72,
      "ma20": 41.64,
      "ma60": null,
      "ma120": null,
      "ma240": null
    },
    {
      "date": "2026-07-06",
      "open": 41.95,
      "high": 42.6,
      "low": 41.2,
      "close": 41.2,
      "volume": 219547.0,
      "ma5": 40.97,
      "ma10": 40.61,
      "ma20": 41.41,
      "ma60": null,
      "ma120": null,
      "ma240": null
    },
    {
      "date": "2026-07-07",
      "open": 40.75,
      "high": 41.0,
      "low": 39.0,
      "close": 39.5,
      "volume": 430090.0,
      "ma5": 40.91,
      "ma10": 40.42,
      "ma20": 41.18,
      "ma60": null,
      "ma120": null,
      "ma240": null
    },
    {
      "date": "2026-07-08",
      "open": 39.8,
      "high": 40.1,
      "low": 38.75,
      "close": 39.9,
      "volume": 169840.0,
      "ma5": 40.89,
      "ma10": 40.33,
      "ma20": 40.96,
      "ma60": null,
      "ma120": null,
      "ma240": null
    },
    {
      "date": "2026-07-09",
      "open": 39.95,
      "high": 40.45,
      "low": 39.6,
      "close": 39.8,
      "volume": 148449.0,
      "ma5": 40.47,
      "ma10": 40.25,
      "ma20": 40.8,
      "ma60": null,
      "ma120": null,
      "ma240": null
    },
    {
      "date": "2026-07-13",
      "open": 40.75,
      "high": 43.75,
      "low": 40.35,
      "close": 43.75,
      "volume": 1677658.0,
      "ma5": 40.83,
      "ma10": 40.7,
      "ma20": 40.9,
      "ma60": null,
      "ma120": null,
      "ma240": null
    }
  ],
  "margin": [
    {
      "date": "2026-05-28",
      "fin_balance": null,
      "mar_balance": null
    },
    {
      "date": "2026-05-29",
      "fin_balance": null,
      "mar_balance": null
    },
    {
      "date": "2026-06-01",
      "fin_balance": null,
      "mar_balance": null
    },
    {
      "date": "2026-06-02",
      "fin_balance": null,
      "mar_balance": null
    },
    {
      "date": "2026-06-03",
      "fin_balance": null,
      "mar_balance": null
    },
    {
      "date": "2026-06-04",
      "fin_balance": null,
      "mar_balance": null
    },
    {
      "date": "2026-06-05",
      "fin_balance": null,
      "mar_balance": null
    },
    {
      "date": "2026-06-08",
      "fin_balance": null,
      "mar_balance": null
    },
    {
      "date": "2026-06-09",
      "fin_balance": null,
      "mar_balance": null
    },
    {
      "date": "2026-06-10",
      "fin_balance": null,
      "mar_balance": null
    },
    {
      "date": "2026-06-11",
      "fin_balance": null,
      "mar_balance": null
    },
    {
      "date": "2026-06-12",
      "fin_balance": null,
      "mar_balance": null
    },
    {
      "date": "2026-06-15",
      "fin_balance": null,
      "mar_balance": null
    },
    {
      "date": "2026-06-16",
      "fin_balance": null,
      "mar_balance": null
    },
    {
      "date": "2026-06-17",
      "fin_balance": null,
      "mar_balance": null
    },
    {
      "date": "2026-06-18",
      "fin_balance": null,
      "mar_balance": null
    },
    {
      "date": "2026-06-22",
      "fin_balance": null,
      "mar_balance": null
    },
    {
      "date": "2026-06-23",
      "fin_balance": null,
      "mar_balance": null
    },
    {
      "date": "2026-06-24",
      "fin_balance": null,
      "mar_balance": null
    },
    {
      "date": "2026-06-25",
      "fin_balance": null,
      "mar_balance": null
    },
    {
      "date": "2026-06-26",
      "fin_balance": null,
      "mar_balance": null
    },
    {
      "date": "2026-06-29",
      "fin_balance": null,
      "mar_balance": null
    },
    {
      "date": "2026-06-30",
      "fin_balance": null,
      "mar_balance": null
    },
    {
      "date": "2026-07-01",
      "fin_balance": null,
      "mar_balance": null
    },
    {
      "date": "2026-07-02",
      "fin_balance": null,
      "mar_balance": null
    },
    {
      "date": "2026-07-03",
      "fin_balance": null,
      "mar_balance": null
    },
    {
      "date": "2026-07-06",
      "fin_balance": null,
      "mar_balance": null
    },
    {
      "date": "2026-07-07",
      "fin_balance": null,
      "mar_balance": null
    },
    {
      "date": "2026-07-08",
      "fin_balance": null,
      "mar_balance": null
    },
    {
      "date": "2026-07-09",
      "fin_balance": null,
      "mar_balance": null
    }
  ],
  "institutional": [
    {
      "date": "2026-05-29",
      "foreign_buy_sell": 279000.0,
      "trust_buy_sell": 0.0,
      "prop_buy_sell": -1153.0,
      "total_inst_buy_sell": 277847.0
    },
    {
      "date": "2026-06-01",
      "foreign_buy_sell": 121292.0,
      "trust_buy_sell": 0.0,
      "prop_buy_sell": 3341.0,
      "total_inst_buy_sell": 124633.0
    },
    {
      "date": "2026-06-02",
      "foreign_buy_sell": -92000.0,
      "trust_buy_sell": 0.0,
      "prop_buy_sell": 59580.0,
      "total_inst_buy_sell": -32420.0
    },
    {
      "date": "2026-06-03",
      "foreign_buy_sell": -143897.0,
      "trust_buy_sell": 0.0,
      "prop_buy_sell": -132.0,
      "total_inst_buy_sell": -144029.0
    },
    {
      "date": "2026-06-04",
      "foreign_buy_sell": -41000.0,
      "trust_buy_sell": 0.0,
      "prop_buy_sell": -2280.0,
      "total_inst_buy_sell": -43280.0
    },
    {
      "date": "2026-06-05",
      "foreign_buy_sell": -48000.0,
      "trust_buy_sell": 0.0,
      "prop_buy_sell": -4775.0,
      "total_inst_buy_sell": -52775.0
    },
    {
      "date": "2026-06-08",
      "foreign_buy_sell": 108000.0,
      "trust_buy_sell": 0.0,
      "prop_buy_sell": -6.0,
      "total_inst_buy_sell": 107994.0
    },
    {
      "date": "2026-06-09",
      "foreign_buy_sell": 96000.0,
      "trust_buy_sell": 0.0,
      "prop_buy_sell": -1.0,
      "total_inst_buy_sell": 95999.0
    },
    {
      "date": "2026-06-10",
      "foreign_buy_sell": -188000.0,
      "trust_buy_sell": 0.0,
      "prop_buy_sell": -1.0,
      "total_inst_buy_sell": -188001.0
    },
    {
      "date": "2026-06-11",
      "foreign_buy_sell": -76000.0,
      "trust_buy_sell": 0.0,
      "prop_buy_sell": 488.0,
      "total_inst_buy_sell": -75512.0
    },
    {
      "date": "2026-06-12",
      "foreign_buy_sell": -14000.0,
      "trust_buy_sell": 0.0,
      "prop_buy_sell": 0.0,
      "total_inst_buy_sell": -14000.0
    },
    {
      "date": "2026-06-15",
      "foreign_buy_sell": 12000.0,
      "trust_buy_sell": 0.0,
      "prop_buy_sell": -35.0,
      "total_inst_buy_sell": 11965.0
    },
    {
      "date": "2026-06-16",
      "foreign_buy_sell": 8000.0,
      "trust_buy_sell": 0.0,
      "prop_buy_sell": 723.0,
      "total_inst_buy_sell": 8723.0
    },
    {
      "date": "2026-06-17",
      "foreign_buy_sell": 31000.0,
      "trust_buy_sell": 0.0,
      "prop_buy_sell": -80.0,
      "total_inst_buy_sell": 30920.0
    },
    {
      "date": "2026-06-18",
      "foreign_buy_sell": 50000.0,
      "trust_buy_sell": 0.0,
      "prop_buy_sell": 609.0,
      "total_inst_buy_sell": 50609.0
    },
    {
      "date": "2026-06-22",
      "foreign_buy_sell": 76000.0,
      "trust_buy_sell": 0.0,
      "prop_buy_sell": 0.0,
      "total_inst_buy_sell": 76000.0
    },
    {
      "date": "2026-06-23",
      "foreign_buy_sell": -158000.0,
      "trust_buy_sell": 0.0,
      "prop_buy_sell": -99.0,
      "total_inst_buy_sell": -158099.0
    },
    {
      "date": "2026-06-24",
      "foreign_buy_sell": -87000.0,
      "trust_buy_sell": 0.0,
      "prop_buy_sell": -685.0,
      "total_inst_buy_sell": -87685.0
    },
    {
      "date": "2026-06-25",
      "foreign_buy_sell": 4040.0,
      "trust_buy_sell": 0.0,
      "prop_buy_sell": -23052.0,
      "total_inst_buy_sell": -19012.0
    },
    {
      "date": "2026-06-26",
      "foreign_buy_sell": -38900.0,
      "trust_buy_sell": 0.0,
      "prop_buy_sell": -830.0,
      "total_inst_buy_sell": -39730.0
    },
    {
      "date": "2026-06-29",
      "foreign_buy_sell": 11000.0,
      "trust_buy_sell": 0.0,
      "prop_buy_sell": -17.0,
      "total_inst_buy_sell": 10983.0
    },
    {
      "date": "2026-06-30",
      "foreign_buy_sell": 11000.0,
      "trust_buy_sell": 0.0,
      "prop_buy_sell": 0.0,
      "total_inst_buy_sell": 11000.0
    },
    {
      "date": "2026-07-01",
      "foreign_buy_sell": 75000.0,
      "trust_buy_sell": 0.0,
      "prop_buy_sell": 511.0,
      "total_inst_buy_sell": 75511.0
    },
    {
      "date": "2026-07-02",
      "foreign_buy_sell": -22743.0,
      "trust_buy_sell": 0.0,
      "prop_buy_sell": 890.0,
      "total_inst_buy_sell": -21853.0
    },
    {
      "date": "2026-07-03",
      "foreign_buy_sell": -11890.0,
      "trust_buy_sell": 0.0,
      "prop_buy_sell": -153.0,
      "total_inst_buy_sell": -12043.0
    },
    {
      "date": "2026-07-06",
      "foreign_buy_sell": 6000.0,
      "trust_buy_sell": 0.0,
      "prop_buy_sell": 0.0,
      "total_inst_buy_sell": 6000.0
    },
    {
      "date": "2026-07-07",
      "foreign_buy_sell": -74934.0,
      "trust_buy_sell": 0.0,
      "prop_buy_sell": 130.0,
      "total_inst_buy_sell": -74804.0
    },
    {
      "date": "2026-07-08",
      "foreign_buy_sell": -9000.0,
      "trust_buy_sell": 0.0,
      "prop_buy_sell": -201.0,
      "total_inst_buy_sell": -9201.0
    },
    {
      "date": "2026-07-09",
      "foreign_buy_sell": 30000.0,
      "trust_buy_sell": 0.0,
      "prop_buy_sell": -1104.0,
      "total_inst_buy_sell": 28896.0
    }
  ],
  "tdcc": [
    {
      "date": "20260529",
      "levels": [
        {
          "level": "1-10張",
          "ratio": 0.54
        },
        {
          "level": "11-50張",
          "ratio": 14.62
        },
        {
          "level": "51-100張",
          "ratio": 6.53
        },
        {
          "level": "101-200張",
          "ratio": 3.06
        },
        {
          "level": "201-400張",
          "ratio": 2.35
        },
        {
          "level": "401-600張",
          "ratio": 2.39
        },
        {
          "level": "601-800張",
          "ratio": 1.62
        },
        {
          "level": "801-1000張",
          "ratio": 1.34
        },
        {
          "level": "1001-2000張",
          "ratio": 3.99
        },
        {
          "level": "2001張以上",
          "ratio": 3.81
        }
      ]
    },
    {
      "date": "20260605",
      "levels": [
        {
          "level": "1-10張",
          "ratio": 0.54
        },
        {
          "level": "11-50張",
          "ratio": 14.27
        },
        {
          "level": "51-100張",
          "ratio": 6.62
        },
        {
          "level": "101-200張",
          "ratio": 2.95
        },
        {
          "level": "201-400張",
          "ratio": 2.06
        },
        {
          "level": "401-600張",
          "ratio": 2.59
        },
        {
          "level": "601-800張",
          "ratio": 1.7
        },
        {
          "level": "801-1000張",
          "ratio": 1.48
        },
        {
          "level": "1001-2000張",
          "ratio": 4.2
        },
        {
          "level": "2001張以上",
          "ratio": 3.96
        }
      ]
    },
    {
      "date": "20260612",
      "levels": [
        {
          "level": "1-10張",
          "ratio": 0.53
        },
        {
          "level": "11-50張",
          "ratio": 13.95
        },
        {
          "level": "51-100張",
          "ratio": 6.38
        },
        {
          "level": "101-200張",
          "ratio": 3.08
        },
        {
          "level": "201-400張",
          "ratio": 2.19
        },
        {
          "level": "401-600張",
          "ratio": 2.47
        },
        {
          "level": "601-800張",
          "ratio": 1.61
        },
        {
          "level": "801-1000張",
          "ratio": 1.42
        },
        {
          "level": "1001-2000張",
          "ratio": 3.76
        },
        {
          "level": "2001張以上",
          "ratio": 4.32
        }
      ]
    },
    {
      "date": "20260618",
      "levels": [
        {
          "level": "1-10張",
          "ratio": 0.53
        },
        {
          "level": "11-50張",
          "ratio": 13.9
        },
        {
          "level": "51-100張",
          "ratio": 6.41
        },
        {
          "level": "101-200張",
          "ratio": 2.92
        },
        {
          "level": "201-400張",
          "ratio": 2.21
        },
        {
          "level": "401-600張",
          "ratio": 2.59
        },
        {
          "level": "601-800張",
          "ratio": 1.84
        },
        {
          "level": "801-1000張",
          "ratio": 1.35
        },
        {
          "level": "1001-2000張",
          "ratio": 4.01
        },
        {
          "level": "2001張以上",
          "ratio": 4.32
        }
      ]
    },
    {
      "date": "20260626",
      "levels": [
        {
          "level": "1-10張",
          "ratio": 0.53
        },
        {
          "level": "11-50張",
          "ratio": 13.8
        },
        {
          "level": "51-100張",
          "ratio": 6.42
        },
        {
          "level": "101-200張",
          "ratio": 2.98
        },
        {
          "level": "201-400張",
          "ratio": 2.06
        },
        {
          "level": "401-600張",
          "ratio": 2.63
        },
        {
          "level": "601-800張",
          "ratio": 1.76
        },
        {
          "level": "801-1000張",
          "ratio": 1.47
        },
        {
          "level": "1001-2000張",
          "ratio": 4.4
        },
        {
          "level": "2001張以上",
          "ratio": 4.35
        }
      ]
    },
    {
      "date": "20260703",
      "levels": [
        {
          "level": "1-10張",
          "ratio": 0.53
        },
        {
          "level": "11-50張",
          "ratio": 13.7
        },
        {
          "level": "51-100張",
          "ratio": 6.6
        },
        {
          "level": "101-200張",
          "ratio": 2.89
        },
        {
          "level": "201-400張",
          "ratio": 2.14
        },
        {
          "level": "401-600張",
          "ratio": 2.54
        },
        {
          "level": "601-800張",
          "ratio": 1.74
        },
        {
          "level": "801-1000張",
          "ratio": 1.41
        },
        {
          "level": "1001-2000張",
          "ratio": 4.68
        },
        {
          "level": "2001張以上",
          "ratio": 4.35
        }
      ]
    }
  ]
}