{
  "stock_id": "6945",
  "stock_name": "圓祥生技",
  "updated_at": "2026-07-15T19:36:18",
  "price": [
    {
      "date": "2026-06-05",
      "open": 102.0,
      "high": 107.0,
      "low": 98.3,
      "close": 105.0,
      "volume": 2632045.0,
      "ma5": null,
      "ma10": null,
      "ma20": null,
      "ma60": null,
      "ma120": null,
      "ma240": null
    },
    {
      "date": "2026-06-08",
      "open": 99.9,
      "high": 105.0,
      "low": 97.1,
      "close": 104.0,
      "volume": 521018.0,
      "ma5": null,
      "ma10": null,
      "ma20": null,
      "ma60": null,
      "ma120": null,
      "ma240": null
    },
    {
      "date": "2026-06-09",
      "open": 104.0,
      "high": 104.0,
      "low": 101.5,
      "close": 102.0,
      "volume": 281852.0,
      "ma5": null,
      "ma10": null,
      "ma20": null,
      "ma60": null,
      "ma120": null,
      "ma240": null
    },
    {
      "date": "2026-06-10",
      "open": 102.0,
      "high": 104.5,
      "low": 101.0,
      "close": 102.0,
      "volume": 332001.0,
      "ma5": null,
      "ma10": null,
      "ma20": null,
      "ma60": null,
      "ma120": null,
      "ma240": null
    },
    {
      "date": "2026-06-11",
      "open": 102.0,
      "high": 104.0,
      "low": 99.9,
      "close": 100.0,
      "volume": 314946.0,
      "ma5": 102.6,
      "ma10": null,
      "ma20": null,
      "ma60": null,
      "ma120": null,
      "ma240": null
    },
    {
      "date": "2026-06-12",
      "open": 101.0,
      "high": 101.5,
      "low": 97.8,
      "close": 99.9,
      "volume": 333555.0,
      "ma5": 101.58,
      "ma10": null,
      "ma20": null,
      "ma60": null,
      "ma120": null,
      "ma240": null
    },
    {
      "date": "2026-06-15",
      "open": 100.0,
      "high": 102.5,
      "low": 99.2,
      "close": 102.5,
      "volume": 366538.0,
      "ma5": 101.28,
      "ma10": null,
      "ma20": null,
      "ma60": null,
      "ma120": null,
      "ma240": null
    },
    {
      "date": "2026-06-16",
      "open": 104.0,
      "high": 106.0,
      "low": 100.0,
      "close": 100.5,
      "volume": 276985.0,
      "ma5": 100.98,
      "ma10": null,
      "ma20": null,
      "ma60": null,
      "ma120": null,
      "ma240": null
    },
    {
      "date": "2026-06-17",
      "open": 101.0,
      "high": 101.0,
      "low": 98.1,
      "close": 98.5,
      "volume": 339697.0,
      "ma5": 100.28,
      "ma10": null,
      "ma20": null,
      "ma60": null,
      "ma120": null,
      "ma240": null
    },
    {
      "date": "2026-06-18",
      "open": 97.6,
      "high": 99.0,
      "low": 95.0,
      "close": 98.9,
      "volume": 465053.0,
      "ma5": 100.06,
      "ma10": 101.33,
      "ma20": null,
      "ma60": null,
      "ma120": null,
      "ma240": null
    },
    {
      "date": "2026-06-22",
      "open": 99.0,
      "high": 105.0,
      "low": 98.5,
      "close": 102.0,
      "volume": 523089.0,
      "ma5": 100.48,
      "ma10": 101.03,
      "ma20": null,
      "ma60": null,
      "ma120": null,
      "ma240": null
    },
    {
      "date": "2026-06-23",
      "open": 102.0,
      "high": 102.0,
      "low": 99.2,
      "close": 100.0,
      "volume": 265701.0,
      "ma5": 99.98,
      "ma10": 100.63,
      "ma20": null,
      "ma60": null,
      "ma120": null,
      "ma240": null
    },
    {
      "date": "2026-06-24",
      "open": 100.0,
      "high": 100.0,
      "low": 98.0,
      "close": 99.5,
      "volume": 195834.0,
      "ma5": 99.78,
      "ma10": 100.38,
      "ma20": null,
      "ma60": null,
      "ma120": null,
      "ma240": null
    },
    {
      "date": "2026-06-25",
      "open": 100.0,
      "high": 100.0,
      "low": 97.5,
      "close": 97.7,
      "volume": 209317.0,
      "ma5": 99.62,
      "ma10": 99.95,
      "ma20": null,
      "ma60": null,
      "ma120": null,
      "ma240": null
    },
    {
      "date": "2026-06-26",
      "open": 97.7,
      "high": 98.6,
      "low": 92.5,
      "close": 94.8,
      "volume": 430460.0,
      "ma5": 98.8,
      "ma10": 99.43,
      "ma20": null,
      "ma60": null,
      "ma120": null,
      "ma240": null
    },
    {
      "date": "2026-06-29",
      "open": 96.9,
      "high": 100.5,
      "low": 94.3,
      "close": 99.9,
      "volume": 303966.0,
      "ma5": 98.38,
      "ma10": 99.43,
      "ma20": null,
      "ma60": null,
      "ma120": null,
      "ma240": null
    },
    {
      "date": "2026-06-30",
      "open": 100.0,
      "high": 103.0,
      "low": 98.0,
      "close": 101.0,
      "volume": 295006.0,
      "ma5": 98.58,
      "ma10": 99.28,
      "ma20": null,
      "ma60": null,
      "ma120": null,
      "ma240": null
    },
    {
      "date": "2026-07-01",
      "open": 101.0,
      "high": 101.0,
      "low": 97.2,
      "close": 97.2,
      "volume": 198898.0,
      "ma5": 98.12,
      "ma10": 98.95,
      "ma20": null,
      "ma60": null,
      "ma120": null,
      "ma240": null
    },
    {
      "date": "2026-07-02",
      "open": 98.5,
      "high": 98.5,
      "low": 96.0,
      "close": 97.5,
      "volume": 93903.0,
      "ma5": 98.08,
      "ma10": 98.85,
      "ma20": null,
      "ma60": null,
      "ma120": null,
      "ma240": null
    },
    {
      "date": "2026-07-03",
      "open": 97.9,
      "high": 107.0,
      "low": 97.9,
      "close": 105.0,
      "volume": 673043.0,
      "ma5": 100.12,
      "ma10": 99.46,
      "ma20": 100.4,
      "ma60": null,
      "ma120": null,
      "ma240": null
    },
    {
      "date": "2026-07-06",
      "open": 106.5,
      "high": 109.5,
      "low": 103.0,
      "close": 104.5,
      "volume": 602760.0,
      "ma5": 101.04,
      "ma10": 99.71,
      "ma20": 100.37,
      "ma60": null,
      "ma120": null,
      "ma240": null
    },
    {
      "date": "2026-07-07",
      "open": 106.0,
      "high": 114.5,
      "low": 104.0,
      "close": 114.5,
      "volume": 1092860.0,
      "ma5": 103.74,
      "ma10": 101.16,
      "ma20": 100.9,
      "ma60": null,
      "ma120": null,
      "ma240": null
    },
    {
      "date": "2026-07-08",
      "open": 120.5,
      "high": 120.5,
      "low": 110.0,
      "close": 118.0,
      "volume": 1507220.0,
      "ma5": 107.9,
      "ma10": 103.01,
      "ma20": 101.7,
      "ma60": null,
      "ma120": null,
      "ma240": null
    },
    {
      "date": "2026-07-09",
      "open": 115.5,
      "high": 119.5,
      "low": 112.0,
      "close": 112.0,
      "volume": 686770.0,
      "ma5": 110.8,
      "ma10": 104.44,
      "ma20": 102.2,
      "ma60": null,
      "ma120": null,
      "ma240": null
    },
    {
      "date": "2026-07-13",
      "open": 113.0,
      "high": 113.5,
      "low": 107.5,
      "close": 108.0,
      "volume": 322443.0,
      "ma5": 111.4,
      "ma10": 105.76,
      "ma20": 102.59,
      "ma60": null,
      "ma120": null,
      "ma240": null
    },
    {
      "date": "2026-07-14",
      "open": 108.0,
      "high": 111.5,
      "low": 104.0,
      "close": 106.5,
      "volume": 290828.0,
      "ma5": 111.8,
      "ma10": 106.42,
      "ma20": 102.92,
      "ma60": null,
      "ma120": null,
      "ma240": null
    },
    {
      "date": "2026-07-15",
      "open": 107.0,
      "high": 116.0,
      "low": 106.0,
      "close": 112.0,
      "volume": 458783.0,
      "ma5": 111.3,
      "ma10": 107.52,
      "ma20": 103.4,
      "ma60": null,
      "ma120": null,
      "ma240": null
    }
  ],
  "margin": [],
  "institutional": [
    {
      "date": "2026-06-05",
      "foreign_buy_sell": -274000.0,
      "trust_buy_sell": 0.0,
      "prop_buy_sell": -66.0,
      "total_inst_buy_sell": -274066.0
    },
    {
      "date": "2026-06-08",
      "foreign_buy_sell": 68000.0,
      "trust_buy_sell": 0.0,
      "prop_buy_sell": 0.0,
      "total_inst_buy_sell": 68000.0
    },
    {
      "date": "2026-06-09",
      "foreign_buy_sell": -53571.0,
      "trust_buy_sell": 0.0,
      "prop_buy_sell": 0.0,
      "total_inst_buy_sell": -53571.0
    },
    {
      "date": "2026-06-10",
      "foreign_buy_sell": 70980.0,
      "trust_buy_sell": 0.0,
      "prop_buy_sell": 0.0,
      "total_inst_buy_sell": 70980.0
    },
    {
      "date": "2026-06-11",
      "foreign_buy_sell": -60591.0,
      "trust_buy_sell": 0.0,
      "prop_buy_sell": 0.0,
      "total_inst_buy_sell": -60591.0
    },
    {
      "date": "2026-06-12",
      "foreign_buy_sell": 87890.0,
      "trust_buy_sell": 0.0,
      "prop_buy_sell": -1048.0,
      "total_inst_buy_sell": 86842.0
    },
    {
      "date": "2026-06-15",
      "foreign_buy_sell": 201000.0,
      "trust_buy_sell": 0.0,
      "prop_buy_sell": -15066.0,
      "total_inst_buy_sell": 185934.0
    },
    {
      "date": "2026-06-16",
      "foreign_buy_sell": -87000.0,
      "trust_buy_sell": 0.0,
      "prop_buy_sell": -10000.0,
      "total_inst_buy_sell": -97000.0
    },
    {
      "date": "2026-06-17",
      "foreign_buy_sell": -177000.0,
      "trust_buy_sell": 0.0,
      "prop_buy_sell": -25000.0,
      "total_inst_buy_sell": -202000.0
    },
    {
      "date": "2026-06-18",
      "foreign_buy_sell": 144000.0,
      "trust_buy_sell": 0.0,
      "prop_buy_sell": -2000.0,
      "total_inst_buy_sell": 142000.0
    },
    {
      "date": "2026-06-22",
      "foreign_buy_sell": 60900.0,
      "trust_buy_sell": 0.0,
      "prop_buy_sell": -20000.0,
      "total_inst_buy_sell": 40900.0
    },
    {
      "date": "2026-06-23",
      "foreign_buy_sell": -12000.0,
      "trust_buy_sell": 0.0,
      "prop_buy_sell": -3000.0,
      "total_inst_buy_sell": -15000.0
    },
    {
      "date": "2026-06-24",
      "foreign_buy_sell": -3200.0,
      "trust_buy_sell": 0.0,
      "prop_buy_sell": -5904.0,
      "total_inst_buy_sell": -9104.0
    },
    {
      "date": "2026-06-25",
      "foreign_buy_sell": -94000.0,
      "trust_buy_sell": 0.0,
      "prop_buy_sell": -15000.0,
      "total_inst_buy_sell": -109000.0
    },
    {
      "date": "2026-06-26",
      "foreign_buy_sell": 10000.0,
      "trust_buy_sell": 0.0,
      "prop_buy_sell": 0.0,
      "total_inst_buy_sell": 10000.0
    },
    {
      "date": "2026-06-29",
      "foreign_buy_sell": 72094.0,
      "trust_buy_sell": 0.0,
      "prop_buy_sell": 0.0,
      "total_inst_buy_sell": 72094.0
    },
    {
      "date": "2026-06-30",
      "foreign_buy_sell": 39000.0,
      "trust_buy_sell": 0.0,
      "prop_buy_sell": 0.0,
      "total_inst_buy_sell": 39000.0
    },
    {
      "date": "2026-07-01",
      "foreign_buy_sell": 4000.0,
      "trust_buy_sell": 0.0,
      "prop_buy_sell": 0.0,
      "total_inst_buy_sell": 4000.0
    },
    {
      "date": "2026-07-02",
      "foreign_buy_sell": -12000.0,
      "trust_buy_sell": 0.0,
      "prop_buy_sell": 0.0,
      "total_inst_buy_sell": -12000.0
    },
    {
      "date": "2026-07-03",
      "foreign_buy_sell": 77000.0,
      "trust_buy_sell": 0.0,
      "prop_buy_sell": 556.0,
      "total_inst_buy_sell": 77556.0
    },
    {
      "date": "2026-07-06",
      "foreign_buy_sell": 80000.0,
      "trust_buy_sell": 0.0,
      "prop_buy_sell": -556.0,
      "total_inst_buy_sell": 79444.0
    },
    {
      "date": "2026-07-07",
      "foreign_buy_sell": 269000.0,
      "trust_buy_sell": 0.0,
      "prop_buy_sell": 10917.0,
      "total_inst_buy_sell": 279917.0
    },
    {
      "date": "2026-07-08",
      "foreign_buy_sell": -250215.0,
      "trust_buy_sell": 0.0,
      "prop_buy_sell": -10000.0,
      "total_inst_buy_sell": -260215.0
    },
    {
      "date": "2026-07-09",
      "foreign_buy_sell": -61821.0,
      "trust_buy_sell": 0.0,
      "prop_buy_sell": 25083.0,
      "total_inst_buy_sell": -36738.0
    },
    {
      "date": "2026-07-13",
      "foreign_buy_sell": 48778.0,
      "trust_buy_sell": 0.0,
      "prop_buy_sell": 0.0,
      "total_inst_buy_sell": 48778.0
    },
    {
      "date": "2026-07-14",
      "foreign_buy_sell": -4478.0,
      "trust_buy_sell": 0.0,
      "prop_buy_sell": 0.0,
      "total_inst_buy_sell": -4478.0
    },
    {
      "date": "2026-07-15",
      "foreign_buy_sell": -44000.0,
      "trust_buy_sell": 0.0,
      "prop_buy_sell": 3.0,
      "total_inst_buy_sell": -43997.0
    }
  ],
  "tdcc": [
    {
      "date": "20260605",
      "levels": [
        {
          "level": "1-10張",
          "ratio": 0.28
        },
        {
          "level": "11-50張",
          "ratio": 7.49
        },
        {
          "level": "51-100張",
          "ratio": 3.34
        },
        {
          "level": "101-200張",
          "ratio": 1.93
        },
        {
          "level": "201-400張",
          "ratio": 2.09
        },
        {
          "level": "401-600張",
          "ratio": 3.16
        },
        {
          "level": "601-800張",
          "ratio": 1.83
        },
        {
          "level": "801-1000張",
          "ratio": 1.76
        },
        {
          "level": "1001-2000張",
          "ratio": 4.63
        },
        {
          "level": "2001張以上",
          "ratio": 5.73
        }
      ]
    },
    {
      "date": "20260612",
      "levels": [
        {
          "level": "1-10張",
          "ratio": 0.29
        },
        {
          "level": "11-50張",
          "ratio": 7.1
        },
        {
          "level": "51-100張",
          "ratio": 3.54
        },
        {
          "level": "101-200張",
          "ratio": 2.13
        },
        {
          "level": "201-400張",
          "ratio": 2.08
        },
        {
          "level": "401-600張",
          "ratio": 2.85
        },
        {
          "level": "601-800張",
          "ratio": 1.91
        },
        {
          "level": "801-1000張",
          "ratio": 1.8
        },
        {
          "level": "1001-2000張",
          "ratio": 4.75
        },
        {
          "level": "2001張以上",
          "ratio": 5.79
        }
      ]
    },
    {
      "date": "20260618",
      "levels": [
        {
          "level": "1-10張",
          "ratio": 0.29
        },
        {
          "level": "11-50張",
          "ratio": 7.1
        },
        {
          "level": "51-100張",
          "ratio": 3.58
        },
        {
          "level": "101-200張",
          "ratio": 2.08
        },
        {
          "level": "201-400張",
          "ratio": 2.04
        },
        {
          "level": "401-600張",
          "ratio": 2.98
        },
        {
          "level": "601-800張",
          "ratio": 1.87
        },
        {
          "level": "801-1000張",
          "ratio": 1.7
        },
        {
          "level": "1001-2000張",
          "ratio": 5.08
        },
        {
          "level": "2001張以上",
          "ratio": 5.8
        }
      ]
    },
    {
      "date": "20260626",
      "levels": [
        {
          "level": "1-10張",
          "ratio": 0.3
        },
        {
          "level": "11-50張",
          "ratio": 7.03
        },
        {
          "level": "51-100張",
          "ratio": 3.49
        },
        {
          "level": "101-200張",
          "ratio": 2.22
        },
        {
          "level": "201-400張",
          "ratio": 1.91
        },
        {
          "level": "401-600張",
          "ratio": 2.98
        },
        {
          "level": "601-800張",
          "ratio": 2.02
        },
        {
          "level": "801-1000張",
          "ratio": 1.61
        },
        {
          "level": "1001-2000張",
          "ratio": 5.38
        },
        {
          "level": "2001張以上",
          "ratio": 5.42
        }
      ]
    },
    {
      "date": "20260703",
      "levels": [
        {
          "level": "1-10張",
          "ratio": 0.3
        },
        {
          "level": "11-50張",
          "ratio": 6.92
        },
        {
          "level": "51-100張",
          "ratio": 3.52
        },
        {
          "level": "101-200張",
          "ratio": 2.15
        },
        {
          "level": "201-400張",
          "ratio": 2.03
        },
        {
          "level": "401-600張",
          "ratio": 2.88
        },
        {
          "level": "601-800張",
          "ratio": 1.85
        },
        {
          "level": "801-1000張",
          "ratio": 1.71
        },
        {
          "level": "1001-2000張",
          "ratio": 5.54
        },
        {
          "level": "2001張以上",
          "ratio": 5.46
        }
      ]
    },
    {
      "date": "20260709",
      "levels": [
        {
          "level": "1-10張",
          "ratio": 0.31
        },
        {
          "level": "11-50張",
          "ratio": 6.51
        },
        {
          "level": "51-100張",
          "ratio": 3.78
        },
        {
          "level": "101-200張",
          "ratio": 2.24
        },
        {
          "level": "201-400張",
          "ratio": 2.27
        },
        {
          "level": "401-600張",
          "ratio": 2.92
        },
        {
          "level": "601-800張",
          "ratio": 1.91
        },
        {
          "level": "801-1000張",
          "ratio": 1.66
        },
        {
          "level": "1001-2000張",
          "ratio": 5.04
        },
        {
          "level": "2001張以上",
          "ratio": 5.58
        }
      ]
    }
  ]
}